kiwi_menu/__init__.py
kiwi_menu-1.0.3.dist-info/METADATA
kiwi_menu-1.0.3.dist-info/WHEEL
kiwi_menu-1.0.3.dist-info/top_level.txt
kiwi_menu-1.0.3.dist-info/RECORD
