Metadata-Version: 2.1
Name: kiwi-menu
Version: 1.0.3
Summary: A simple terminal menu for python
Home-page: UNKNOWN
Author: mi66mc
Author-email: miguelmalgarezi@gmail.com
License: MIT
Keywords: menu
Platform: UNKNOWN
Classifier: Development Status :: 5 - Production/Stable
Classifier: Intended Audience :: Education
Classifier: Operating System :: Microsoft :: Windows :: Windows 10
Classifier: License :: OSI Approved :: MIT License
Classifier: Programming Language :: Python :: 3
Requires-Dist: keyboard
